archerv2/__init__.py
archerv2/_compat.py
archerv2/_server.py
archerv2/app.py
archerv2/cli.py
archerv2/config.py
archerv2/event.py
archerv2/helper.py
archerv2/logger.py
archerv2/test.py
archerv2-0.6.dist-info/DESCRIPTION.rst
archerv2-0.6.dist-info/METADATA
archerv2-0.6.dist-info/RECORD
archerv2-0.6.dist-info/WHEEL
archerv2-0.6.dist-info/entry_points.txt
archerv2-0.6.dist-info/metadata.json
archerv2-0.6.dist-info/top_level.txt
