Metadata-Version: 2.0
Name: archerv2
Version: 0.6
Summary: Thrift app the flask way...The Right Way
Home-page: https://github.com/dstarner15/archerv2
Author: Daniel Starner
Author-email: starner.daniel5@gmail.com
License: MIT
Platform: UNKNOWN
Classifier: Development Status :: 3 - Alpha
Classifier: Environment :: Other Environment
Classifier: Intended Audience :: Developers
Classifier: License :: OSI Approved :: MIT License
Classifier: Operating System :: MacOS :: MacOS X
Classifier: Operating System :: POSIX
Classifier: Programming Language :: Python
Classifier: Programming Language :: Python :: 2.7
Classifier: Programming Language :: Python :: 3.2
Classifier: Programming Language :: Python :: 3.3
Classifier: Programming Language :: Python :: 3.4
Classifier: Topic :: Utilities
Classifier: Topic :: Software Development :: Libraries :: Python Modules
Requires-Dist: click (>=3.3)
Requires-Dist: thriftpy (>=0.3.9)
